README.md
setup.py
bigread/__init__.py
bigread/reader.py
bigread.egg-info/PKG-INFO
bigread.egg-info/SOURCES.txt
bigread.egg-info/dependency_links.txt
bigread.egg-info/requires.txt
bigread.egg-info/top_level.txt