Metadata-Version: 1.0
Name: bigread
Version: 0.0.4
Summary: Stream huge files with minimal RAM usage
Home-page: https://github.com/duhaime/bigread
Author: Douglas Duhaime
Author-email: douglas.duhaime@gmail.com
License: MIT
Keywords: text-mining,large-files,streaming
Platform: UNKNOWN
